TextQuoter/__init__.py
TextQuoter/quotetext.py
TextQuoter-0.0.1.2.dist-info/LICENSE
TextQuoter-0.0.1.2.dist-info/METADATA
TextQuoter-0.0.1.2.dist-info/WHEEL
TextQuoter-0.0.1.2.dist-info/top_level.txt
TextQuoter-0.0.1.2.dist-info/RECORD
