Metadata-Version: 2.1
Name: TextQuoter
Version: 0.0.1.2
Summary: TextQuoter is a versatile Python script designed to simplify the processing of quotation marks in a given string.
Home-page: https://github.com/gr1336/TextQuoter/
Author: gr1336
License: MIT License
Classifier: Topic :: Text Editors
Classifier: Topic :: Text Editors :: Text Processing
Classifier: Topic :: Text Editors :: Word Processors
Classifier: Topic :: Text Processing :: Filters
Classifier: Topic :: Text Processing
Classifier: Topic :: Text Processing :: General
Classifier: Topic :: Utilities
Classifier: License :: OSI Approved :: MIT License
License-File: LICENSE
